aioadaptive/__init__.py
aioadaptive/py.typed
aioadaptive/client/__init__.py
aioadaptive/client/_adaptive_client.py
aioadaptive/limiter/__init__.py
aioadaptive/limiter/_limiter.py
aioadaptive/limiter/_vegas.py
aioadaptive-0.1.5.dist-info/METADATA
aioadaptive-0.1.5.dist-info/WHEEL
aioadaptive-0.1.5.dist-info/licenses/LICENSE.txt
aioadaptive-0.1.5.dist-info/RECORD
