Metadata-Version: 2.4
Name: aioadaptive
Version: 0.1.5
Summary: Add your description here
Project-URL: Homepage, https://github.com/swrap/aioadaptive
Project-URL: Documentation, https://github.com/swrap/aioadaptive#readme
Project-URL: Source, https://github.com/swrap/aioadaptive
Project-URL: Tracker, https://github.com/swrap/aioadaptive/issues
Author-email: Jesse Saran <8915311+swrap@users.noreply.github.com>
License-Expression: MIT
License-File: LICENSE.txt
Keywords: adaptive,aiohttp,asyncio,python
Classifier: Development Status :: 3 - Alpha
Classifier: Intended Audience :: Developers
Classifier: License :: OSI Approved :: MIT License
Classifier: Operating System :: OS Independent
Classifier: Programming Language :: Python :: 3
Classifier: Programming Language :: Python :: 3.9
Classifier: Programming Language :: Python :: 3.10
Classifier: Programming Language :: Python :: 3.11
Classifier: Programming Language :: Python :: 3.12
Classifier: Programming Language :: Python :: 3.13
Classifier: Topic :: Software Development :: Libraries :: Python Modules
Requires-Python: >=3.9
Requires-Dist: anyio>=3.0.0
